ceonstock_db/README.md
ceonstock_db/__init__.py
ceonstock_db/alembic.ini
ceonstock_db/database.py
ceonstock_db/errors.py
ceonstock_db/main.py
ceonstock_db/py.typed
ceonstock_db/setup.py
ceonstock_db/_auth/__init__.py
ceonstock_db/_auth/_auth_bearer.py
ceonstock_db/_auth/_auth_handler.py
ceonstock_db/_auth/security.py
ceonstock_db/alembic/README
ceonstock_db/alembic/env.py
ceonstock_db/alembic/how_to.txt
ceonstock_db/alembic/script.py.mako
ceonstock_db/alembic/versions/4cec02cae1c1_baseline.py
ceonstock_db/alembic/versions/b05758151eac_added_stripe_tbl_and_crud.py
ceonstock_db/crud/ABOUT.md
ceonstock_db/crud/__init__.py
ceonstock_db/crud/_job.py
ceonstock_db/crud/_project.py
ceonstock_db/crud/_session.py
ceonstock_db/crud/access_control.py
ceonstock_db/crud/job.py
ceonstock_db/crud/oauth_account.py
ceonstock_db/crud/project.py
ceonstock_db/crud/security.py
ceonstock_db/crud/stripe.py
ceonstock_db/crud/submission.py
ceonstock_db/crud/user.py
ceonstock_db/crud/user_credit.py
ceonstock_db/models/__init__.py
ceonstock_db/models/_security.py
ceonstock_db/models/_user.py
ceonstock_db/models/access_control.py
ceonstock_db/models/job.py
ceonstock_db/models/order.py
ceonstock_db/models/product.py
ceonstock_db/models/project.py
ceonstock_db/models/stripe.py
ceonstock_db/models/submission.py
ceonstock_db/models/user.py
ceonstock_db/models/user_credit.py
ceonstock_db/schemas/README.md
ceonstock_db/schemas/__init__.py
ceonstock_db/schemas/_schemas.py
ceonstock_db/schemas/access_control.py
ceonstock_db/schemas/job.py
ceonstock_db/schemas/project.py
ceonstock_db/schemas/user.py
ceonstock_db/tests/__init__.py
ceonstock_db/tests/_test_users.py
ceonstock_db/tests/conftest.py
ceonstock_db/tests/test_crud_access_control.py
ceonstock_db/tests/test_crud_email_verification_token.py
ceonstock_db/tests/test_crud_project_create.py
ceonstock_db/tests/test_crud_user_create.py
ceonstock_db/tests/test_crud_user_read.py
ceonstock_db-0.8.0.dist-info/METADATA
ceonstock_db-0.8.0.dist-info/WHEEL
ceonstock_db-0.8.0.dist-info/RECORD
